aio_quakeml_client/__init__.py
aio_quakeml_client/__version__.py
aio_quakeml_client/consts.py
aio_quakeml_client/feed.py
aio_quakeml_client/feed_entry.py
aio_quakeml_client/feed_manager.py
aio_quakeml_client/status_update.py
aio_quakeml_client/xml_parser/__init__.py
aio_quakeml_client/xml_parser/creation_info.py
aio_quakeml_client/xml_parser/description.py
aio_quakeml_client/xml_parser/element.py
aio_quakeml_client/xml_parser/event.py
aio_quakeml_client/xml_parser/event_parameters.py
aio_quakeml_client/xml_parser/magnitude.py
aio_quakeml_client/xml_parser/origin.py
aio_quakeml_client-0.8.dist-info/LICENSE
aio_quakeml_client-0.8.dist-info/METADATA
aio_quakeml_client-0.8.dist-info/WHEEL
aio_quakeml_client-0.8.dist-info/top_level.txt
aio_quakeml_client-0.8.dist-info/RECORD
