Metadata-Version: 2.1
Name: aio-quakeml-client
Version: 0.8
Summary: An async QuakeML client library.
Home-page: https://github.com/exxamalte/python-aio-quakeml-client
Author: Malte Franken
Author-email: coding@subspace.de
License: Apache-2.0
Classifier: Programming Language :: Python :: 3.9
Classifier: Programming Language :: Python :: 3.10
Classifier: Programming Language :: Python :: 3.11
Classifier: Programming Language :: Python :: 3.12
Classifier: License :: OSI Approved :: Apache Software License
Classifier: Operating System :: OS Independent
License-File: LICENSE
Requires-Dist: aiohttp <4,>=3.7.4
Requires-Dist: haversine >=2.8.1
Requires-Dist: xmltodict >=0.13.0
Requires-Dist: dateparser >=1.2.0
